nameko_twilio.py
nameko_twilio-0.1.dist-info/DESCRIPTION.rst
nameko_twilio-0.1.dist-info/METADATA
nameko_twilio-0.1.dist-info/RECORD
nameko_twilio-0.1.dist-info/WHEEL
nameko_twilio-0.1.dist-info/metadata.json
nameko_twilio-0.1.dist-info/top_level.txt
